Metadata-Version: 2.4
Name: hashing-mcp
Version: 1.6.0
Summary: An MCP Server offering tools to calculate MD5 and SHA-256 cryptographic hashes for text data, designed for use with LLMs.
Project-URL: Repository, https://github.com/kanad13/MCP-Server-for-Hashing
Project-URL: Documentation, https://www.kunal-pathak.com/blog/model-context-protocol/
Author-email: Kunal Pathak <contact@kunal-pathak.com>
License: MIT
License-File: LICENSE
Keywords: ai,hashing,llm,mcp,md5,sha256,tools
Classifier: Development Status :: 3 - Alpha
Classifier: Intended Audience :: Developers
Classifier: License :: OSI Approved :: MIT License
Classifier: Operating System :: OS Independent
Classifier: Programming Language :: Python :: 3
Classifier: Programming Language :: Python :: 3.10
Classifier: Programming Language :: Python :: 3.11
Classifier: Programming Language :: Python :: 3.12
Classifier: Topic :: Scientific/Engineering :: Artificial Intelligence
Classifier: Topic :: Security :: Cryptography
Classifier: Topic :: Software Development :: Libraries :: Python Modules
Requires-Python: >=3.10
Requires-Dist: mcp[cli]>=1.6.0
Provides-Extra: dev
Requires-Dist: pytest-asyncio; extra == 'dev'
Requires-Dist: pytest>=7.0; extra == 'dev'
Requires-Dist: ruff; extra == 'dev'
